csp_scan/__init__.py
csp_scan/__main__.py
csp_scan/definitions.py
csp_scan/directive.py
csp_scan-1.0.0.dist-info/LICENSE
csp_scan-1.0.0.dist-info/METADATA
csp_scan-1.0.0.dist-info/WHEEL
csp_scan-1.0.0.dist-info/entry_points.txt
csp_scan-1.0.0.dist-info/top_level.txt
csp_scan-1.0.0.dist-info/RECORD
