Metadata-Version: 2.1
Name: csp-scan
Version: 1.0.0
Summary: Constructs strict Content-Security-Policy header after scanning all HTML files in a directory
Home-page: https://github.com/martinezpl/csp-scan
Author: Marcin Szleszynski
Author-email: mszlesz@gmail.com
License: MIT
Platform: UNKNOWN
Classifier: Programming Language :: Python :: 3
Classifier: License :: OSI Approved :: MIT License
Requires-Python: >=3.0
License-File: LICENSE
